dencrypt/__init__.py
dencrypt/base/__init__.py
dencrypt/base/dencrypt_base.py
dencrypt/base/dencrypt_file_base.py
dencrypt/base/load_save_base.py
dencrypt/cli.py
dencrypt/core/__init__.py
dencrypt/core/crypt.py
dencrypt/core/decrypt.py
dencrypt/core/decrypt_file.py
dencrypt/core/encrypt.py
dencrypt/core/encrypt_file.py
dencrypt/exception/__init__.py
dencrypt/exception/existing_key.py
dencrypt/exception/file_overwrite.py
dencrypt/exception/invalid_content.py
dencrypt/exception/invalid_key.py
dencrypt/exception/unknown_key.py
dencrypt/support/__init__.py
dencrypt/support/key_file.py
dencrypt-0.1.1.dist-info/entry_points.txt
dencrypt-0.1.1.dist-info/LICENSE
dencrypt-0.1.1.dist-info/WHEEL
dencrypt-0.1.1.dist-info/METADATA
dencrypt-0.1.1.dist-info/RECORD
