Metadata-Version: 2.1
Name: dencrypt
Version: 0.1.1
Summary: Quickly generates the encryption of texts and files. Using RSA and Fernet as a base.
Home-page: https://github.com/edvitor13/dencrypt
License: MIT
Author: Vitor Gabriel
Author-email: edvitor13@hotmail.com
Requires-Python: >=3.9,<4.0
Classifier: License :: OSI Approved :: MIT License
Classifier: Programming Language :: Python :: 3
Classifier: Programming Language :: Python :: 3.10
Classifier: Programming Language :: Python :: 3.9
Requires-Dist: cryptography (>=35.0.0,<36.0.0)
Requires-Dist: rsa (>=4.7.2,<5.0.0)
Project-URL: Repository, https://github.com/edvitor13/dencrypt
